[{"mCalorie":0.0,"mDistance":0.0,"mNowHealthyStep":0,"mRunStepCount":0,"mSpeed":0.0,"mStartTime":1691899200000,"mStepCount":0,"mTimeUnit":600000,"mTotalActiveTime":0.0,"mWalkStepCount":0},{"mCalorie":0.0,"mDistance":0.0,"mNowHealthyStep":0,"mRunStepCount":0,"mSpeed":0.0,"mStartTime":1691899800000,"mStepCount":0,"mTimeUnit":600000,"mTotalActiveTime":0.0,"mWalkStepCount":0},{"mCalorie":0.0,"mDistance":0.0,"mNowHealthyStep":0,"mRunStepCount":0,"mSpeed":0.0,"mStartTime":1691900400000,"mStepCount":0,"mTimeUnit":600000,"mTotalActiveTime":0.0,"mWalkStepCount":0},{"mCalorie":0.0,"mDistance":0.0,"mNowHealthyStep":0,"mRunStepCount":0,"mSpeed":0.0,"mStartTime":1691901000000,"mStepCount":0,"mTimeUnit":600000,"mTotalActiveTime":0.0,"mWalkStepCount":0},{"mCalorie":0.41999998688697815,"mDistance":8.429999828338623,"mNowHealthyStep":0,"mRunStepCount":0,"mSpeed":3.2492902278900146,"mStartTime":1691901600000,"mStepCount":12,"mTimeUnit":600000,"mTotalActiveTime":9339.885841011259,"mWalkStepCount":12},{"mCalorie":0.0,"mDistance":0.0,"mNowHealthyStep":0,"mRunStepCount":0,"mSpeed":0.0,"mStartTime":1691902200000,"mStepCount":0,"mTimeUnit":600000,"mTotalActiveTime":0.0,"mWalkStepCount":0},{"mCalorie":5.950000017881393,"mDistance":117.34000015258789,"mNowHealthyStep":0,"mRunStepCount":0,"mSpeed":4.328295707702637,"mStartTime":1691902800000,"mStepCount":158,"mTimeUnit":600000,"mTotalActiveTime":97595.91733583009,"mWalkStepCount":158},{"mCalorie":4.18000003695488,"mDistance":90.59000301361084,"mNowHealthyStep":0,"mRunStepCount":0,"mSpeed":4.243616104125977,"mStartTime":1691903400000,"mStepCount":123,"mTimeUnit":600000,"mTotalActiveTime":76850.5003187704,"mWalkStepCount":123},{"mCalorie":2.650000024586916,"mDistance":50.62000012397766,"mNowHealthyStep":0,"mRunStepCount":0,"mSpeed":4.3700361251831055,"mStartTime":1691904000000,"mStepCount":68,"mTimeUnit":600000,"mTotalActiveTime":41700.340259868855,"mWalkStepCount":68},{"mCalorie":5.189999982714653,"mDistance":84.81999969482422,"mNowHealthyStep":0,"mRunStepCount":1,"mSpeed":4.401933193206787,"mStartTime":1691904600000,"mStepCount":114,"mTimeUnit":600000,"mTotalActiveTime":69367.70195324114,"mWalkStepCount":113},{"mCalorie":9.959863245487213,"mDistance":190.5243730545044,"mNowHealthyStep":0,"mRunStepCount":3,"mSpeed":4.567666053771973,"mStartTime":1691905200000,"mStepCount":252,"mTimeUnit":600000,"mTotalActiveTime":150161.53861432767,"mWalkStepCount":249},{"mCalorie":1.9600976407527924,"mDistance":33.75218725204468,"mNowHealthyStep":0,"mRunStepCount":3,"mSpeed":5.540524959564209,"mStartTime":1691905800000,"mStepCount":43,"mTimeUnit":600000,"mTotalActiveTime":21930.751522926254,"mWalkStepCount":40},{"mCalorie":0.0,"mDistance":0.0,"mNowHealthyStep":0,"mRunStepCount":0,"mSpeed":0.0,"mStartTime":1691906400000,"mStepCount":0,"mTimeUnit":600000,"mTotalActiveTime":0.0,"mWalkStepCount":0},{"mCalorie":0.0,"mDistance":0.0,"mNowHealthyStep":0,"mRunStepCount":0,"mSpeed":0.0,"mStartTime":1691907000000,"mStepCount":0,"mTimeUnit":600000,"mTotalActiveTime":0.0,"mWalkStepCount":0},{"mCalorie":0.23000000417232513,"mDistance":5.199999809265137,"mNowHealthyStep":0,"mRunStepCount":0,"mSpeed":4.113749980926514,"mStartTime":1691907600000,"mStepCount":7,"mTimeUnit":600000,"mTotalActiveTime":4550.592379252544,"mWalkStepCount":7},{"mCalorie":0.0,"mDistance":0.0,"mNowHealthyStep":0,"mRunStepCount":0,"mSpeed":0.0,"mStartTime":1691908200000,"mStepCount":0,"mTimeUnit":600000,"mTotalActiveTime":0.0,"mWalkStepCount":0},{"mCalorie":0.0,"mDistance":0.0,"mNowHealthyStep":0,"mRunStepCount":0,"mSpeed":0.0,"mStartTime":1691908800000,"mStepCount":0,"mTimeUnit":600000,"mTotalActiveTime":0.0,"mWalkStepCount":0},{"mCalorie":0.0,"mDistance":0.0,"mNowHealthyStep":0,"mRunStepCount":0,"mSpeed":0.0,"mStartTime":1691909400000,"mStepCount":0,"mTimeUnit":600000,"mTotalActiveTime":0.0,"mWalkStepCount":0},{"mCalorie":0.0,"mDistance":0.0,"mNowHealthyStep":0,"mRunStepCount":0,"mSpeed":0.0,"mStartTime":1691910000000,"mStepCount":0,"mTimeUnit":600000,"mTotalActiveTime":0.0,"mWalkStepCount":0},{"mCalorie":0.0,"mDistance":0.0,"mNowHealthyStep":0,"mRunStepCount":0,"mSpeed":0.0,"mStartTime":1691910600000,"mStepCount":0,"mTimeUnit":600000,"mTotalActiveTime":0.0,"mWalkStepCount":0},{"mCalorie":0.0,"mDistance":0.0,"mNowHealthyStep":0,"mRunStepCount":0,"mSpeed":0.0,"mStartTime":1691911200000,"mStepCount":0,"mTimeUnit":600000,"mTotalActiveTime":0.0,"mWalkStepCount":0},{"mCalorie":0.0,"mDistance":0.0,"mNowHealthyStep":0,"mRunStepCount":0,"mSpeed":0.0,"mStartTime":1691911800000,"mStepCount":0,"mTimeUnit":600000,"mTotalActiveTime":0.0,"mWalkStepCount":0},{"mCalorie":0.0,"mDistance":0.0,"mNowHealthyStep":0,"mRunStepCount":0,"mSpeed":0.0,"mStartTime":1691912400000,"mStepCount":0,"mTimeUnit":600000,"mTotalActiveTime":0.0,"mWalkStepCount":0},{"mCalorie":0.0,"mDistance":0.0,"mNowHealthyStep":0,"mRunStepCount":0,"mSpeed":0.0,"mStartTime":1691913000000,"mStepCount":0,"mTimeUnit":600000,"mTotalActiveTime":0.0,"mWalkStepCount":0},{"mCalorie":0.0,"mDistance":0.0,"mNowHealthyStep":0,"mRunStepCount":0,"mSpeed":0.0,"mStartTime":1691913600000,"mStepCount":0,"mTimeUnit":600000,"mTotalActiveTime":0.0,"mWalkStepCount":0},{"mCalorie":0.0,"mDistance":0.0,"mNowHealthyStep":0,"mRunStepCount":0,"mSpeed":0.0,"mStartTime":1691914200000,"mStepCount":0,"mTimeUnit":600000,"mTotalActiveTime":0.0,"mWalkStepCount":0},{"mCalorie":0.0,"mDistance":0.0,"mNowHealthyStep":0,"mRunStepCount":0,"mSpeed":0.0,"mStartTime":1691914800000,"mStepCount":0,"mTimeUnit":600000,"mTotalActiveTime":0.0,"mWalkStepCount":0},{"mCalorie":0.0,"mDistance":0.0,"mNowHealthyStep":0,"mRunStepCount":0,"mSpeed":0.0,"mStartTime":1691915400000,"mStepCount":0,"mTimeUnit":600000,"mTotalActiveTime":0.0,"mWalkStepCount":0},{"mCalorie":0.0,"mDistance":0.0,"mNowHealthyStep":0,"mRunStepCount":0,"mSpeed":0.0,"mStartTime":1691916000000,"mStepCount":0,"mTimeUnit":600000,"mTotalActiveTime":0.0,"mWalkStepCount":0},{"mCalorie":0.0,"mDistance":0.0,"mNowHealthyStep":0,"mRunStepCount":0,"mSpeed":0.0,"mStartTime":1691916600000,"mStepCount":0,"mTimeUnit":600000,"mTotalActiveTime":0.0,"mWalkStepCount":0},{"mCalorie":0.0,"mDistance":0.0,"mNowHealthyStep":0,"mRunStepCount":0,"mSpeed":0.0,"mStartTime":1691917200000,"mStepCount":0,"mTimeUnit":600000,"mTotalActiveTime":0.0,"mWalkStepCount":0},{"mCalorie":0.0,"mDistance":0.0,"mNowHealthyStep":0,"mRunStepCount":0,"mSpeed":0.0,"mStartTime":1691917800000,"mStepCount":0,"mTimeUnit":600000,"mTotalActiveTime":0.0,"mWalkStepCount":0},{"mCalorie":0.0,"mDistance":0.0,"mNowHealthyStep":0,"mRunStepCount":0,"mSpeed":0.0,"mStartTime":1691918400000,"mStepCount":0,"mTimeUnit":600000,"mTotalActiveTime":0.0,"mWalkStepCount":0},{"mCalorie":0.0,"mDistance":0.0,"mNowHealthyStep":0,"mRunStepCount":0,"mSpeed":0.0,"mStartTime":1691919000000,"mStepCount":0,"mTimeUnit":600000,"mTotalActiveTime":0.0,"mWalkStepCount":0},{"mCalorie":0.0,"mDistance":0.0,"mNowHealthyStep":0,"mRunStepCount":0,"mSpeed":0.0,"mStartTime":1691919600000,"mStepCount":0,"mTimeUnit":600000,"mTotalActiveTime":0.0,"mWalkStepCount":0},{"mCalorie":0.0,"mDistance":0.0,"mNowHealthyStep":0,"mRunStepCount":0,"mSpeed":0.0,"mStartTime":1691920200000,"mStepCount":0,"mTimeUnit":600000,"mTotalActiveTime":0.0,"mWalkStepCount":0},{"mCalorie":0.0,"mDistance":0.0,"mNowHealthyStep":0,"mRunStepCount":0,"mSpeed":0.0,"mStartTime":1691920800000,"mStepCount":0,"mTimeUnit":600000,"mTotalActiveTime":0.0,"mWalkStepCount":0},{"mCalorie":0.0,"mDistance":0.0,"mNowHealthyStep":0,"mRunStepCount":0,"mSpeed":0.0,"mStartTime":1691921400000,"mStepCount":0,"mTimeUnit":600000,"mTotalActiveTime":0.0,"mWalkStepCount":0},{"mCalorie":0.0,"mDistance":0.0,"mNowHealthyStep":0,"mRunStepCount":0,"mSpeed":0.0,"mStartTime":1691922000000,"mStepCount":0,"mTimeUnit":600000,"mTotalActiveTime":0.0,"mWalkStepCount":0},{"mCalorie":0.0,"mDistance":0.0,"mNowHealthyStep":0,"mRunStepCount":0,"mSpeed":0.0,"mStartTime":1691922600000,"mStepCount":0,"mTimeUnit":600000,"mTotalActiveTime":0.0,"mWalkStepCount":0},{"mCalorie":0.0,"mDistance":0.0,"mNowHealthyStep":0,"mRunStepCount":0,"mSpeed":0.0,"mStartTime":1691923200000,"mStepCount":0,"mTimeUnit":600000,"mTotalActiveTime":0.0,"mWalkStepCount":0},{"mCalorie":0.0,"mDistance":0.0,"mNowHealthyStep":0,"mRunStepCount":0,"mSpeed":0.0,"mStartTime":1691923800000,"mStepCount":0,"mTimeUnit":600000,"mTotalActiveTime":0.0,"mWalkStepCount":0},{"mCalorie":0.0,"mDistance":0.0,"mNowHealthyStep":0,"mRunStepCount":0,"mSpeed":0.0,"mStartTime":1691924400000,"mStepCount":0,"mTimeUnit":600000,"mTotalActiveTime":0.0,"mWalkStepCount":0},{"mCalorie":0.0,"mDistance":0.0,"mNowHealthyStep":0,"mRunStepCount":0,"mSpeed":0.0,"mStartTime":1691925000000,"mStepCount":0,"mTimeUnit":600000,"mTotalActiveTime":0.0,"mWalkStepCount":0},{"mCalorie":0.0,"mDistance":0.0,"mNowHealthyStep":0,"mRunStepCount":0,"mSpeed":0.0,"mStartTime":1691925600000,"mStepCount":0,"mTimeUnit":600000,"mTotalActiveTime":0.0,"mWalkStepCount":0},{"mCalorie":0.0,"mDistance":0.0,"mNowHealthyStep":0,"mRunStepCount":0,"mSpeed":0.0,"mStartTime":1691926200000,"mStepCount":0,"mTimeUnit":600000,"mTotalActiveTime":0.0,"mWalkStepCount":0},{"mCalorie":0.0,"mDistance":0.0,"mNowHealthyStep":0,"mRunStepCount":0,"mSpeed":0.0,"mStartTime":1691926800000,"mStepCount":0,"mTimeUnit":600000,"mTotalActiveTime":0.0,"mWalkStepCount":0},{"mCalorie":0.0,"mDistance":0.0,"mNowHealthyStep":0,"mRunStepCount":0,"mSpeed":0.0,"mStartTime":1691927400000,"mStepCount":0,"mTimeUnit":600000,"mTotalActiveTime":0.0,"mWalkStepCount":0},{"mCalorie":0.0,"mDistance":0.0,"mNowHealthyStep":0,"mRunStepCount":0,"mSpeed":0.0,"mStartTime":1691928000000,"mStepCount":0,"mTimeUnit":600000,"mTotalActiveTime":0.0,"mWalkStepCount":0},{"mCalorie":0.0,"mDistance":0.0,"mNowHealthyStep":0,"mRunStepCount":0,"mSpeed":0.0,"mStartTime":1691928600000,"mStepCount":0,"mTimeUnit":600000,"mTotalActiveTime":0.0,"mWalkStepCount":0},{"mCalorie":0.0,"mDistance":0.0,"mNowHealthyStep":0,"mRunStepCount":0,"mSpeed":0.0,"mStartTime":1691929200000,"mStepCount":0,"mTimeUnit":600000,"mTotalActiveTime":0.0,"mWalkStepCount":0},{"mCalorie":0.0,"mDistance":0.0,"mNowHealthyStep":0,"mRunStepCount":0,"mSpeed":0.0,"mStartTime":1691929800000,"mStepCount":0,"mTimeUnit":600000,"mTotalActiveTime":0.0,"mWalkStepCount":0},{"mCalorie":0.0,"mDistance":0.0,"mNowHealthyStep":0,"mRunStepCount":0,"mSpeed":0.0,"mStartTime":1691930400000,"mStepCount":0,"mTimeUnit":600000,"mTotalActiveTime":0.0,"mWalkStepCount":0},{"mCalorie":0.0,"mDistance":0.0,"mNowHealthyStep":0,"mRunStepCount":0,"mSpeed":0.0,"mStartTime":1691931000000,"mStepCount":0,"mTimeUnit":600000,"mTotalActiveTime":0.0,"mWalkStepCount":0},{"mCalorie":0.0,"mDistance":0.0,"mNowHealthyStep":0,"mRunStepCount":0,"mSpeed":0.0,"mStartTime":1691931600000,"mStepCount":0,"mTimeUnit":600000,"mTotalActiveTime":0.0,"mWalkStepCount":0},{"mCalorie":0.0,"mDistance":0.0,"mNowHealthyStep":0,"mRunStepCount":0,"mSpeed":0.0,"mStartTime":1691932200000,"mStepCount":0,"mTimeUnit":600000,"mTotalActiveTime":0.0,"mWalkStepCount":0},{"mCalorie":0.0,"mDistance":0.0,"mNowHealthyStep":0,"mRunStepCount":0,"mSpeed":0.0,"mStartTime":1691932800000,"mStepCount":0,"mTimeUnit":600000,"mTotalActiveTime":0.0,"mWalkStepCount":0},{"mCalorie":1.1299999952316284,"mDistance":17.790000915527344,"mNowHealthyStep":0,"mRunStepCount":0,"mSpeed":3.700000047683716,"mStartTime":1691933400000,"mStepCount":25,"mTimeUnit":600000,"mTotalActiveTime":17309.189856900528,"mWalkStepCount":25},{"mCalorie":0.0,"mDistance":0.0,"mNowHealthyStep":0,"mRunStepCount":0,"mSpeed":0.0,"mStartTime":1691934000000,"mStepCount":0,"mTimeUnit":600000,"mTotalActiveTime":0.0,"mWalkStepCount":0},{"mCalorie":0.0,"mDistance":0.0,"mNowHealthyStep":0,"mRunStepCount":0,"mSpeed":0.0,"mStartTime":1691934600000,"mStepCount":0,"mTimeUnit":600000,"mTotalActiveTime":0.0,"mWalkStepCount":0},{"mCalorie":5.509804606437683,"mDistance":76.40156173706055,"mNowHealthyStep":0,"mRunStepCount":0,"mSpeed":4.376137733459473,"mStartTime":1691935200000,"mStepCount":103,"mTimeUnit":600000,"mTotalActiveTime":62851.22647451119,"mWalkStepCount":103},{"mCalorie":2.2800000458955765,"mDistance":37.08999967575073,"mNowHealthyStep":0,"mRunStepCount":0,"mSpeed":4.2770304679870605,"mStartTime":1691935800000,"mStepCount":51,"mTimeUnit":600000,"mTotalActiveTime":31218.85731343956,"mWalkStepCount":51},{"mCalorie":2.5100000202655792,"mDistance":36.209999561309814,"mNowHealthyStep":0,"mRunStepCount":0,"mSpeed":4.658550262451172,"mStartTime":1691936400000,"mStepCount":49,"mTimeUnit":600000,"mTotalActiveTime":27982.095426143336,"mWalkStepCount":49},{"mCalorie":1.7300000190734863,"mDistance":22.44000005722046,"mNowHealthyStep":0,"mRunStepCount":0,"mSpeed":3.5580878257751465,"mStartTime":1691937000000,"mStepCount":32,"mTimeUnit":600000,"mTotalActiveTime":22704.33062397424,"mWalkStepCount":32},{"mCalorie":6.009765565395355,"mDistance":110.45593547821045,"mNowHealthyStep":0,"mRunStepCount":0,"mSpeed":4.386335849761963,"mStartTime":1691937600000,"mStepCount":149,"mTimeUnit":600000,"mTotalActiveTime":90654.56438722793,"mWalkStepCount":149},{"mCalorie":3.0800000429153442,"mDistance":60.80000114440918,"mNowHealthyStep":0,"mRunStepCount":0,"mSpeed":5.94998836517334,"mStartTime":1691938200000,"mStepCount":78,"mTimeUnit":600000,"mTotalActiveTime":36786.62733520696,"mWalkStepCount":78},{"mCalorie":0.0,"mDistance":0.0,"mNowHealthyStep":0,"mRunStepCount":0,"mSpeed":0.0,"mStartTime":1691938800000,"mStepCount":0,"mTimeUnit":600000,"mTotalActiveTime":0.0,"mWalkStepCount":0},{"mCalorie":5.2000000067055225,"mDistance":117.61000156402588,"mNowHealthyStep":0,"mRunStepCount":0,"mSpeed":4.796022891998291,"mStartTime":1691939400000,"mStepCount":156,"mTimeUnit":600000,"mTotalActiveTime":88280.6484582703,"mWalkStepCount":156},{"mCalorie":5.129999935626984,"mDistance":110.85000228881836,"mNowHealthyStep":0,"mRunStepCount":0,"mSpeed":4.745471954345703,"mStartTime":1691940000000,"mStepCount":147,"mTimeUnit":600000,"mTotalActiveTime":84092.79847207712,"mWalkStepCount":147},{"mCalorie":0.23000000417232513,"mDistance":5.070000171661377,"mNowHealthyStep":0,"mRunStepCount":0,"mSpeed":4.099999904632568,"mStartTime":1691940600000,"mStepCount":7,"mTimeUnit":600000,"mTotalActiveTime":4451.7075713485065,"mWalkStepCount":7},{"mCalorie":7.18999981880188,"mDistance":161.93999862670898,"mNowHealthyStep":0,"mRunStepCount":0,"mSpeed":4.416278839111328,"mStartTime":1691941200000,"mStepCount":217,"mTimeUnit":600000,"mTotalActiveTime":132007.9718820692,"mWalkStepCount":217},{"mCalorie":6.169999986886978,"mDistance":147.6699981689453,"mNowHealthyStep":0,"mRunStepCount":0,"mSpeed":5.130679607391357,"mStartTime":1691941800000,"mStepCount":193,"mTimeUnit":600000,"mTotalActiveTime":103614.34361307765,"mWalkStepCount":193},{"mCalorie":15.549472570419312,"mDistance":232.8765640258789,"mNowHealthyStep":0,"mRunStepCount":0,"mSpeed":4.572600364685059,"mStartTime":1691942400000,"mStepCount":314,"mTimeUnit":600000,"mTotalActiveTime":183343.30094536048,"mWalkStepCount":314},{"mCalorie":8.399999618530273,"mDistance":185.31998825073242,"mNowHealthyStep":0,"mRunStepCount":0,"mSpeed":4.850835800170898,"mStartTime":1691943000000,"mStepCount":245,"mTimeUnit":600000,"mTotalActiveTime":137533.40937185654,"mWalkStepCount":245},{"mCalorie":0.0,"mDistance":0.0,"mNowHealthyStep":0,"mRunStepCount":0,"mSpeed":0.0,"mStartTime":1691943600000,"mStepCount":0,"mTimeUnit":600000,"mTotalActiveTime":0.0,"mWalkStepCount":0},{"mCalorie":0.0,"mDistance":0.0,"mNowHealthyStep":0,"mRunStepCount":0,"mSpeed":0.0,"mStartTime":1691944200000,"mStepCount":0,"mTimeUnit":600000,"mTotalActiveTime":0.0,"mWalkStepCount":0},{"mCalorie":9.189999967813492,"mDistance":226.50000476837158,"mNowHealthyStep":0,"mRunStepCount":0,"mSpeed":4.872138500213623,"mStartTime":1691944800000,"mStepCount":299,"mTimeUnit":600000,"mTotalActiveTime":167359.78392255976,"mWalkStepCount":299},{"mCalorie":0.20000000298023224,"mDistance":4.340000152587891,"mNowHealthyStep":0,"mRunStepCount":0,"mSpeed":4.299999713897705,"mStartTime":1691945400000,"mStepCount":6,"mTimeUnit":600000,"mTotalActiveTime":3633.4887415967146,"mWalkStepCount":6},{"mCalorie":1.4100000113248825,"mDistance":21.43000030517578,"mNowHealthyStep":0,"mRunStepCount":0,"mSpeed":5.080402851104736,"mStartTime":1691946000000,"mStepCount":28,"mTimeUnit":600000,"mTotalActiveTime":15185.410795560245,"mWalkStepCount":28},{"mCalorie":2.580000013113022,"mDistance":39.05999994277954,"mNowHealthyStep":0,"mRunStepCount":0,"mSpeed":4.482736110687256,"mStartTime":1691946600000,"mStepCount":53,"mTimeUnit":600000,"mTotalActiveTime":31368.343376090997,"mWalkStepCount":53},{"mCalorie":1.6699999570846558,"mDistance":36.84000015258789,"mNowHealthyStep":0,"mRunStepCount":0,"mSpeed":5.085674285888672,"mStartTime":1691947200000,"mStepCount":48,"mTimeUnit":600000,"mTotalActiveTime":26077.958430644154,"mWalkStepCount":48},{"mCalorie":2.909999966621399,"mDistance":67.31000137329102,"mNowHealthyStep":0,"mRunStepCount":0,"mSpeed":4.632286071777344,"mStartTime":1691947800000,"mStepCount":91,"mTimeUnit":600000,"mTotalActiveTime":52310.244221263594,"mWalkStepCount":91},{"mCalorie":0.0,"mDistance":0.0,"mNowHealthyStep":0,"mRunStepCount":0,"mSpeed":0.0,"mStartTime":1691948400000,"mStepCount":0,"mTimeUnit":600000,"mTotalActiveTime":0.0,"mWalkStepCount":0},{"mCalorie":0.47998046875,"mDistance":8.4375,"mNowHealthyStep":0,"mRunStepCount":0,"mSpeed":5.099999904632568,"mStartTime":1691949000000,"mStepCount":11,"mTimeUnit":600000,"mTotalActiveTime":5955.882464313179,"mWalkStepCount":11},{"mCalorie":0.0,"mDistance":0.0,"mNowHealthyStep":0,"mRunStepCount":0,"mSpeed":0.0,"mStartTime":1691949600000,"mStepCount":0,"mTimeUnit":600000,"mTotalActiveTime":0.0,"mWalkStepCount":0},{"mCalorie":4.289999961853027,"mDistance":91.63000106811523,"mNowHealthyStep":0,"mRunStepCount":0,"mSpeed":5.173147201538086,"mStartTime":1691950200000,"mStepCount":114,"mTimeUnit":600000,"mTotalActiveTime":63765.43887782305,"mWalkStepCount":114},{"mCalorie":3.4700000286102295,"mDistance":83.35999870300293,"mNowHealthyStep":0,"mRunStepCount":0,"mSpeed":4.534391403198242,"mStartTime":1691950800000,"mStepCount":111,"mTimeUnit":600000,"mTotalActiveTime":66182.19723013144,"mWalkStepCount":111},{"mCalorie":1.2799999713897705,"mDistance":28.59000015258789,"mNowHealthyStep":0,"mRunStepCount":0,"mSpeed":4.799999713897705,"mStartTime":1691951400000,"mStepCount":39,"mTimeUnit":600000,"mTotalActiveTime":21442.501392513594,"mWalkStepCount":39},{"mCalorie":0.0,"mDistance":0.0,"mNowHealthyStep":0,"mRunStepCount":0,"mSpeed":0.0,"mStartTime":1691952000000,"mStepCount":0,"mTimeUnit":600000,"mTotalActiveTime":0.0,"mWalkStepCount":0},{"mCalorie":0.5899999737739563,"mDistance":8.9399995803833,"mNowHealthyStep":0,"mRunStepCount":0,"mSpeed":4.600000381469727,"mStartTime":1691952600000,"mStepCount":12,"mTimeUnit":600000,"mTotalActiveTime":6996.5208305258675,"mWalkStepCount":12},{"mCalorie":0.0,"mDistance":0.0,"mNowHealthyStep":0,"mRunStepCount":0,"mSpeed":0.0,"mStartTime":1691953200000,"mStepCount":0,"mTimeUnit":600000,"mTotalActiveTime":0.0,"mWalkStepCount":0},{"mCalorie":4.760000020265579,"mDistance":110.0999984741211,"mNowHealthyStep":0,"mRunStepCount":0,"mSpeed":4.360861778259277,"mStartTime":1691953800000,"mStepCount":150,"mTimeUnit":600000,"mTotalActiveTime":90890.29224919158,"mWalkStepCount":150},{"mCalorie":1.2599999904632568,"mDistance":27.130000114440918,"mNowHealthyStep":0,"mRunStepCount":0,"mSpeed":3.623089551925659,"mStartTime":1691954400000,"mStepCount":38,"mTimeUnit":600000,"mTotalActiveTime":26957.102781656613,"mWalkStepCount":38},{"mCalorie":0.5400000214576721,"mDistance":13.109999656677246,"mNowHealthyStep":0,"mRunStepCount":0,"mSpeed":5.199999809265137,"mStartTime":1691955000000,"mStepCount":17,"mTimeUnit":600000,"mTotalActiveTime":9076.153941380206,"mWalkStepCount":17},{"mCalorie":1.7799998372793198,"mDistance":39.829999923706055,"mNowHealthyStep":0,"mRunStepCount":0,"mSpeed":4.786243915557861,"mStartTime":1691955600000,"mStepCount":53,"mTimeUnit":600000,"mTotalActiveTime":29958.35585852847,"mWalkStepCount":53},{"mCalorie":1.3100000023841858,"mDistance":30.78999900817871,"mNowHealthyStep":0,"mRunStepCount":0,"mSpeed":4.696046829223633,"mStartTime":1691956200000,"mStepCount":41,"mTimeUnit":600000,"mTotalActiveTime":23603.681497435937,"mWalkStepCount":41},{"mCalorie":0.36000001430511475,"mDistance":10.920000076293945,"mNowHealthyStep":0,"mRunStepCount":0,"mSpeed":5.199999809265137,"mStartTime":1691956800000,"mStepCount":14,"mTimeUnit":600000,"mTotalActiveTime":7560.000330118044,"mWalkStepCount":14},{"mCalorie":7.999998554587364,"mDistance":173.19999313354492,"mNowHealthyStep":0,"mRunStepCount":0,"mSpeed":4.391421794891357,"mStartTime":1691957400000,"mStepCount":234,"mTimeUnit":600000,"mTotalActiveTime":141985.89667335834,"mWalkStepCount":234},{"mCalorie":1.2500000298023224,"mDistance":19.28000020980835,"mNowHealthyStep":0,"mRunStepCount":0,"mSpeed":5.131077766418457,"mStartTime":1691958000000,"mStepCount":25,"mTimeUnit":600000,"mTotalActiveTime":13526.983372401322,"mWalkStepCount":25},{"mCalorie":2.2700000405311584,"mDistance":35.6200008392334,"mNowHealthyStep":0,"mRunStepCount":0,"mSpeed":4.980945587158203,"mStartTime":1691958600000,"mStepCount":47,"mTimeUnit":600000,"mTotalActiveTime":25744.5106285766,"mWalkStepCount":47},{"mCalorie":0.679999977350235,"mDistance":14.40999984741211,"mNowHealthyStep":0,"mRunStepCount":0,"mSpeed":3.853083610534668,"mStartTime":1691959200000,"mStepCount":20,"mTimeUnit":600000,"mTotalActiveTime":13463.502512771785,"mWalkStepCount":20},{"mCalorie":3.0799999237060547,"mDistance":73.98999977111816,"mNowHealthyStep":0,"mRunStepCount":0,"mSpeed":4.792308330535889,"mStartTime":1691959800000,"mStepCount":98,"mTimeUnit":600000,"mTotalActiveTime":55581.56469624344,"mWalkStepCount":98},{"mCalorie":5.2599999606609344,"mDistance":99.57000207901001,"mNowHealthyStep":0,"mRunStepCount":0,"mSpeed":4.341103553771973,"mStartTime":1691960400000,"mStepCount":136,"mTimeUnit":600000,"mTotalActiveTime":82571.63166428528,"mWalkStepCount":136},{"mCalorie":1.2899999767541885,"mDistance":30.769999980926514,"mNowHealthyStep":0,"mRunStepCount":0,"mSpeed":4.780770778656006,"mStartTime":1691961000000,"mStepCount":41,"mTimeUnit":600000,"mTotalActiveTime":23170.32268026105,"mWalkStepCount":41},{"mCalorie":1.050000011920929,"mDistance":24.439999103546143,"mNowHealthyStep":0,"mRunStepCount":0,"mSpeed":4.500770092010498,"mStartTime":1691961600000,"mStepCount":33,"mTimeUnit":600000,"mTotalActiveTime":19548.653778176475,"mWalkStepCount":33},{"mCalorie":4.5600001364946365,"mDistance":97.21000099182129,"mNowHealthyStep":0,"mRunStepCount":0,"mSpeed":4.94144344329834,"mStartTime":1691962200000,"mStepCount":128,"mTimeUnit":600000,"mTotalActiveTime":70820.60503518631,"mWalkStepCount":128},{"mCalorie":3.5999995470046997,"mDistance":91.09001541137695,"mNowHealthyStep":0,"mRunStepCount":0,"mSpeed":4.866786479949951,"mStartTime":1691962800000,"mStepCount":120,"mTimeUnit":600000,"mTotalActiveTime":67379.99421605887,"mWalkStepCount":120},{"mCalorie":2.3899999856948853,"mDistance":29.82999897003174,"mNowHealthyStep":0,"mRunStepCount":7,"mSpeed":5.303138732910156,"mStartTime":1691963400000,"mStepCount":38,"mTimeUnit":600000,"mTotalActiveTime":20249.89470149658,"mWalkStepCount":31},{"mCalorie":2.799999952316284,"mDistance":45.850000858306885,"mNowHealthyStep":0,"mRunStepCount":2,"mSpeed":4.794557094573975,"mStartTime":1691964000000,"mStepCount":60,"mTimeUnit":600000,"mTotalActiveTime":34426.53769186349,"mWalkStepCount":58},{"mCalorie":2.7599999457597733,"mDistance":52.80999994277954,"mNowHealthyStep":0,"mRunStepCount":0,"mSpeed":4.240776062011719,"mStartTime":1691964600000,"mStepCount":71,"mTimeUnit":600000,"mTotalActiveTime":44830.47457790084,"mWalkStepCount":71},{"mCalorie":2.650078147649765,"mDistance":56.43687438964844,"mNowHealthyStep":0,"mRunStepCount":0,"mSpeed":4.743685722351074,"mStartTime":1691965200000,"mStepCount":74,"mTimeUnit":600000,"mTotalActiveTime":42830.14544442901,"mWalkStepCount":74},{"mCalorie":1.0100000202655792,"mDistance":17.18000030517578,"mNowHealthyStep":0,"mRunStepCount":0,"mSpeed":4.515004634857178,"mStartTime":1691965800000,"mStepCount":23,"mTimeUnit":600000,"mTotalActiveTime":13698.324836121103,"mWalkStepCount":23},{"mCalorie":2.2499999403953552,"mDistance":32.639999866485596,"mNowHealthyStep":0,"mRunStepCount":0,"mSpeed":4.2452921867370605,"mStartTime":1691966400000,"mStepCount":45,"mTimeUnit":600000,"mTotalActiveTime":27678.66000289333,"mWalkStepCount":45},{"mCalorie":1.6299999356269836,"mDistance":24.84000015258789,"mNowHealthyStep":0,"mRunStepCount":0,"mSpeed":4.91078519821167,"mStartTime":1691967000000,"mStepCount":33,"mTimeUnit":600000,"mTotalActiveTime":18209.715026711317,"mWalkStepCount":33},{"mCalorie":4.890000104904175,"mDistance":90.11000061035156,"mNowHealthyStep":0,"mRunStepCount":0,"mSpeed":4.6912126541137695,"mStartTime":1691967600000,"mStepCount":119,"mTimeUnit":600000,"mTotalActiveTime":69149.71363607039,"mWalkStepCount":119},{"mCalorie":2.6299999952316284,"mDistance":57.610000133514404,"mNowHealthyStep":0,"mRunStepCount":0,"mSpeed":4.819119930267334,"mStartTime":1691968200000,"mStepCount":76,"mTimeUnit":600000,"mTotalActiveTime":43036.07188111706,"mWalkStepCount":76},{"mCalorie":2.209999978542328,"mDistance":46.97999858856201,"mNowHealthyStep":0,"mRunStepCount":0,"mSpeed":4.531488418579102,"mStartTime":1691968800000,"mStepCount":63,"mTimeUnit":600000,"mTotalActiveTime":37322.83539088959,"mWalkStepCount":63},{"mCalorie":0.0,"mDistance":0.0,"mNowHealthyStep":0,"mRunStepCount":0,"mSpeed":0.0,"mStartTime":1691969400000,"mStepCount":0,"mTimeUnit":600000,"mTotalActiveTime":0.0,"mWalkStepCount":0},{"mCalorie":0.5799999833106995,"mDistance":8.619999885559082,"mNowHealthyStep":0,"mRunStepCount":0,"mSpeed":4.0,"mStartTime":1691970000000,"mStepCount":12,"mTimeUnit":600000,"mTotalActiveTime":7757.999897003174,"mWalkStepCount":12},{"mCalorie":9.679999887943268,"mDistance":164.45000076293945,"mNowHealthyStep":0,"mRunStepCount":0,"mSpeed":4.871629238128662,"mStartTime":1691970600000,"mStepCount":217,"mTimeUnit":600000,"mTotalActiveTime":121524.0292325638,"mWalkStepCount":217},{"mCalorie":3.319999873638153,"mDistance":78.68000030517578,"mNowHealthyStep":0,"mRunStepCount":0,"mSpeed":4.3993940353393555,"mStartTime":1691971200000,"mStepCount":106,"mTimeUnit":600000,"mTotalActiveTime":64383.41538848341,"mWalkStepCount":106},{"mCalorie":20.819433867931366,"mDistance":335.9237561225891,"mNowHealthyStep":0,"mRunStepCount":0,"mSpeed":5.217343330383301,"mStartTime":1691971800000,"mStepCount":439,"mTimeUnit":600000,"mTotalActiveTime":231789.52087086168,"mWalkStepCount":439},{"mCalorie":23.30902349948883,"mDistance":365.2850065231323,"mNowHealthyStep":0,"mRunStepCount":3,"mSpeed":4.984617233276367,"mStartTime":1691972400000,"mStepCount":482,"mTimeUnit":600000,"mTotalActiveTime":263816.8629309361,"mWalkStepCount":479},{"mCalorie":6.969824314117432,"mDistance":93.16500186920166,"mNowHealthyStep":0,"mRunStepCount":3,"mSpeed":4.6065993309021,"mStartTime":1691973000000,"mStepCount":124,"mTimeUnit":600000,"mTotalActiveTime":72807.2889771627,"mWalkStepCount":121},{"mCalorie":0.0,"mDistance":0.0,"mNowHealthyStep":0,"mRunStepCount":0,"mSpeed":0.0,"mStartTime":1691973600000,"mStepCount":0,"mTimeUnit":600000,"mTotalActiveTime":0.0,"mWalkStepCount":0},{"mCalorie":0.0,"mDistance":0.0,"mNowHealthyStep":0,"mRunStepCount":0,"mSpeed":0.0,"mStartTime":1691974200000,"mStepCount":0,"mTimeUnit":600000,"mTotalActiveTime":0.0,"mWalkStepCount":0},{"mCalorie":0.0,"mDistance":0.0,"mNowHealthyStep":0,"mRunStepCount":0,"mSpeed":0.0,"mStartTime":1691974800000,"mStepCount":0,"mTimeUnit":600000,"mTotalActiveTime":0.0,"mWalkStepCount":0},{"mCalorie":0.0,"mDistance":0.0,"mNowHealthyStep":0,"mRunStepCount":0,"mSpeed":0.0,"mStartTime":1691975400000,"mStepCount":0,"mTimeUnit":600000,"mTotalActiveTime":0.0,"mWalkStepCount":0},{"mCalorie":0.0,"mDistance":0.0,"mNowHealthyStep":0,"mRunStepCount":0,"mSpeed":0.0,"mStartTime":1691976000000,"mStepCount":0,"mTimeUnit":600000,"mTotalActiveTime":0.0,"mWalkStepCount":0},{"mCalorie":1.0799999833106995,"mDistance":18.19000005722046,"mNowHealthyStep":0,"mRunStepCount":0,"mSpeed":4.738282680511475,"mStartTime":1691976600000,"mStepCount":24,"mTimeUnit":600000,"mTotalActiveTime":13820.19653060269,"mWalkStepCount":24},{"mCalorie":13.030000030994415,"mDistance":184.5499973297119,"mNowHealthyStep":0,"mRunStepCount":48,"mSpeed":5.943950653076172,"mStartTime":1691977200000,"mStepCount":232,"mTimeUnit":600000,"mTotalActiveTime":111774.14178351396,"mWalkStepCount":184},{"mCalorie":9.469999432563782,"mDistance":232.7000026702881,"mNowHealthyStep":0,"mRunStepCount":0,"mSpeed":4.783689498901367,"mStartTime":1691977800000,"mStepCount":307,"mTimeUnit":600000,"mTotalActiveTime":175120.06443590578,"mWalkStepCount":307},{"mCalorie":14.009999513626099,"mDistance":282.3299980163574,"mNowHealthyStep":0,"mRunStepCount":0,"mSpeed":4.8289713859558105,"mStartTime":1691978400000,"mStepCount":373,"mTimeUnit":600000,"mTotalActiveTime":210477.12077028034,"mWalkStepCount":373},{"mCalorie":7.149999976158142,"mDistance":175.69000053405762,"mNowHealthyStep":0,"mRunStepCount":0,"mSpeed":4.686152458190918,"mStartTime":1691979000000,"mStepCount":234,"mTimeUnit":600000,"mTotalActiveTime":134968.72151282037,"mWalkStepCount":234},{"mCalorie":0.0,"mDistance":0.0,"mNowHealthyStep":0,"mRunStepCount":0,"mSpeed":0.0,"mStartTime":1691979600000,"mStepCount":0,"mTimeUnit":600000,"mTotalActiveTime":0.0,"mWalkStepCount":0},{"mCalorie":4.429472744464874,"mDistance":82.31968879699707,"mNowHealthyStep":0,"mRunStepCount":0,"mSpeed":4.482708930969238,"mStartTime":1691980200000,"mStepCount":111,"mTimeUnit":600000,"mTotalActiveTime":66109.77249020738,"mWalkStepCount":111},{"mCalorie":0.0,"mDistance":0.0,"mNowHealthyStep":0,"mRunStepCount":0,"mSpeed":0.0,"mStartTime":1691980800000,"mStepCount":0,"mTimeUnit":600000,"mTotalActiveTime":0.0,"mWalkStepCount":0},{"mCalorie":1.5800000429153442,"mDistance":37.189998626708984,"mNowHealthyStep":0,"mRunStepCount":0,"mSpeed":4.400000095367432,"mStartTime":1691981400000,"mStepCount":50,"mTimeUnit":600000,"mTotalActiveTime":30428.18003506704,"mWalkStepCount":50},{"mCalorie":0.0,"mDistance":0.0,"mNowHealthyStep":0,"mRunStepCount":0,"mSpeed":0.0,"mStartTime":1691982000000,"mStepCount":0,"mTimeUnit":600000,"mTotalActiveTime":0.0,"mWalkStepCount":0},{"mCalorie":0.0,"mDistance":0.0,"mNowHealthyStep":0,"mRunStepCount":0,"mSpeed":0.0,"mStartTime":1691982600000,"mStepCount":0,"mTimeUnit":600000,"mTotalActiveTime":0.0,"mWalkStepCount":0},{"mCalorie":0.0,"mDistance":0.0,"mNowHealthyStep":0,"mRunStepCount":0,"mSpeed":0.0,"mStartTime":1691983200000,"mStepCount":0,"mTimeUnit":600000,"mTotalActiveTime":0.0,"mWalkStepCount":0},{"mCalorie":0.0,"mDistance":0.0,"mNowHealthyStep":0,"mRunStepCount":0,"mSpeed":0.0,"mStartTime":1691983800000,"mStepCount":0,"mTimeUnit":600000,"mTotalActiveTime":0.0,"mWalkStepCount":0},{"mCalorie":0.25999999046325684,"mDistance":6.090000152587891,"mNowHealthyStep":0,"mRunStepCount":0,"mSpeed":5.199999809265137,"mStartTime":1691984400000,"mStepCount":8,"mTimeUnit":600000,"mTotalActiveTime":4216.154106439228,"mWalkStepCount":8},{"mCalorie":0.0,"mDistance":0.0,"mNowHealthyStep":0,"mRunStepCount":0,"mSpeed":0.0,"mStartTime":1691985000000,"mStepCount":0,"mTimeUnit":600000,"mTotalActiveTime":0.0,"mWalkStepCount":0}]